<?xml version='1.0' encoding='UTF-8'?>
<package version="0.0.0" uuid="raiserightfoot-a74a19">
 <names>
  <name lang="en_US">RaiseRightFoot</name>
 </names>
 <descriptions>
  <description lang="en_US">This application makes NAO raise its right foot into the air and do a small motion with it.</description>
 </descriptions>
 <supportedLanguages>
  <language>en_US</language>
 </supportedLanguages>
 <descriptionLanguages>
  <language>en_US</language>
 </descriptionLanguages>
 <contents>
  <behaviorContent path="behavior_1">
   <userRequestable/>
   <nature>interactive</nature>
   <names>
    <name lang="en_US">RaiseRightFoot</name>
   </names>
   <descriptions>
    <description lang="en_US">NAO raises its right foot into the air and performs a small motion with it.</description>
   </descriptions>
   <triggerSentences>
    <sentence lang="en_US">Raise your right foot</sentence>
    <sentence lang="en_US">move your right foot</sentence>
    <sentence lang="en_US">raise your right leg</sentence>
    <sentence lang="en_US">move your right leg</sentence>
    <sentence lang="en_US">balance on your left leg</sentence>
   </triggerSentences>
   <loadingResponses>
    <sentence lang="en_US">Raising my right foot</sentence>
   </loadingResponses>
   <autonomous/>
   <permissions/>
  </behaviorContent>
 </contents>
</package>
