<?xml version='1.0' encoding='UTF-8'?>
<package version="0.0.0" uuid="noswearing-e192eb">
 <names>
  <name lang="en_US">NoSwearing</name>
 </names>
 <supportedLanguages>
  <language>en_US</language>
 </supportedLanguages>
 <descriptionLanguages>
  <language>en_US</language>
 </descriptionLanguages>
 <contents>
  <behaviorContent path="behavior_1">
   <userRequestable/>
   <nature>interactive</nature>
   <descriptions>
    <description lang="en_US">Nao should tell the user not to swear when they use foul language
*WARNING*
foul language ahead
list of swear words at:
https://en.wiktionary.org/wiki/Category:English_swear_words
*note*
some of these are really bad, so i mean, if someone says them, nao should certainly be offended by them, but i also feel bad typing them? also, what if Nao mishears someone and they ask him to repeat what they says, and he says something nasty to them? i dont know... like, what if NAO mistakenly drops the the n bomb on somebody? I just have concerns</description>
   </descriptions>
   <triggerSentences>
    <sentence lang="en_US">arse</sentence>
    <sentence lang="en_US">ass</sentence>
    <sentence lang="en_US">asshole</sentence>
    <sentence lang="en_US">bastard</sentence>
    <sentence lang="en_US">bollocks</sentence>
    <sentence lang="en_US">cunt</sentence>
    <sentence lang="en_US">damn</sentence>
    <sentence lang="en_US">fuck</sentence>
    <sentence lang="en_US">god damn</sentence>
    <sentence lang="en_US">holy shit</sentence>
    <sentence lang="en_US">mother fucker</sentence>
    <sentence lang="en_US">nigger</sentence>
    <sentence lang="en_US">shit</sentence>
    <sentence lang="en_US">whore</sentence>
   </triggerSentences>
   <autonomous>
    <condition purpose="launchTrigger"><![CDATA[('Launchpad/NumPeopleZone3'>0)&&('Launchpad/PreviousActivity' != 'noswearing-e192eb/behavior_1')]]></condition>
   </autonomous>
   <permissions/>
  </behaviorContent>
 </contents>
</package>
